sheshe/__init__.py
sheshe/cheche.py
sheshe/chuchu.py
sheshe/mbc_fast.py
sheshe/meta_optimization.py
sheshe/modal_scout_ensemble.py
sheshe/openai_text.py
sheshe/region_interpretability.py
sheshe/sheshe.py
sheshe/shushu.py
sheshe/subspace_scout.py
sheshe-0.1.14.dist-info/licenses/LICENSE
sheshe-0.1.14.dist-info/METADATA
sheshe-0.1.14.dist-info/WHEEL
sheshe-0.1.14.dist-info/top_level.txt
sheshe-0.1.14.dist-info/RECORD
