Metadata-Version: 2.4
Name: sheshe
Version: 0.1.14
Summary: SheShe: Smart High-dimensional Edge Segmentation & Hyperboundary Explorer
Home-page: https://example.com/sheshe
Author: JC + ChatGPT
License: MIT
Classifier: Programming Language :: Python :: 3
Classifier: License :: OSI Approved :: MIT License
Classifier: Operating System :: OS Independent
Classifier: Development Status :: 3 - Alpha
Classifier: Intended Audience :: Science/Research
Classifier: Topic :: Scientific/Engineering :: Artificial Intelligence
Requires-Python: >=3.9
License-File: LICENSE
Requires-Dist: numpy
Requires-Dist: pandas
Requires-Dist: scikit-learn>=1.1
Requires-Dist: matplotlib
Provides-Extra: dev
Requires-Dist: pytest; extra == "dev"
Requires-Dist: seaborn; extra == "dev"
Requires-Dist: hnswlib; extra == "dev"
Requires-Dist: numba; extra == "dev"
Provides-Extra: numba
Requires-Dist: numba; extra == "numba"
Dynamic: author
Dynamic: classifier
Dynamic: description
Dynamic: description-content-type
Dynamic: home-page
Dynamic: license
Dynamic: license-file
Dynamic: provides-extra
Dynamic: requires-dist
Dynamic: requires-python
Dynamic: summary
